LICENSE
README.rst
setup.py
pismosendlogs/__init__.py
pismosendlogs/sendlogs.py
pismosendlogs.egg-info/PKG-INFO
pismosendlogs.egg-info/SOURCES.txt
pismosendlogs.egg-info/dependency_links.txt
pismosendlogs.egg-info/requires.txt
pismosendlogs.egg-info/top_level.txt