Metadata-Version: 2.1
Name: pismosendlogs
Version: 0.2.0
Summary: A library to send logs
Home-page: UNKNOWN
Author: Pismo Data Team
Author-email: 
License: BSD 2-clause
Platform: UNKNOWN
License-File: LICENSE
